sphera/__init__.py
sphera/find_rainbow_clique.py
sphera/process_graph.py
sphera-0.2.0.dist-info/licenses/LICENSE.txt
sphera-0.2.0.dist-info/METADATA
sphera-0.2.0.dist-info/WHEEL
sphera-0.2.0.dist-info/top_level.txt
sphera-0.2.0.dist-info/RECORD
