Metadata-Version: 2.4
Name: sphera
Version: 0.2.0
Summary: A python package containing SPHERA algorithm for efficient Rainbow Clique detection.
Home-page: https://github.com/louzounlab/SPHERA
Author: Devora Siminovsky
Author-email: devorasimi@gmail.com
Classifier: Programming Language :: Python :: 3
Classifier: License :: OSI Approved :: MIT License
Classifier: Operating System :: OS Independent
Requires-Python: >=3.6
License-File: LICENSE.txt
Requires-Dist: numpy>=1.26.4
Requires-Dist: networkx>=3.4.2
Dynamic: license-file
